minifzf/__init__.py
minifzf/_cli/__init__.py
minifzf/_key.py
minifzf/_style.py
minifzf/search.py
minifzf/selector.py
minifzf-0.1.4.dist-info/entry_points.txt
minifzf-0.1.4.dist-info/METADATA
minifzf-0.1.4.dist-info/WHEEL
minifzf-0.1.4.dist-info/RECORD
