Metadata-Version: 2.1
Name: minifzf
Version: 0.1.4
Summary: Python Library and Command Line Tool for Fuzzy Selection.
Author: Harsh Verma
Author-email: synacktra.work@gmail.com
Requires-Python: >=3.8,<4.0
Classifier: Programming Language :: Python :: 3
Classifier: Programming Language :: Python :: 3.8
Classifier: Programming Language :: Python :: 3.9
Classifier: Programming Language :: Python :: 3.10
Classifier: Programming Language :: Python :: 3.11
Classifier: Programming Language :: Python :: 3.12
Requires-Dist: cyclopts (==2.1.2)
Requires-Dist: regex (==2023.12.25)
Requires-Dist: rich (==13.7.0)
Requires-Dist: sshkeyboard (==2.3.1)
